dt_helper/__init__.py
dt_helper/settings.ini
dt_helper-0.1.0.dist-info/LICENSE.txt
dt_helper-0.1.0.dist-info/METADATA
dt_helper-0.1.0.dist-info/WHEEL
dt_helper-0.1.0.dist-info/top_level.txt
dt_helper-0.1.0.dist-info/RECORD
