Metadata-Version: 2.1
Name: dt-helper
Version: 0.1.0
Summary: Helper funcs for doing things with datetime objects and UTC floats
Home-page: https://github.com/kenjyco/dt-helper
Download-URL: https://github.com/kenjyco/dt-helper/tarball/v0.1.0
Author: Ken
Author-email: kenjyco@gmail.com
License: MIT
Keywords: datetime,date,time,utc,helper,kenjyco
Platform: UNKNOWN
Classifier: Development Status :: 4 - Beta
Classifier: Environment :: Console
Classifier: Intended Audience :: Developers
Classifier: License :: OSI Approved :: MIT License
Classifier: Operating System :: MacOS :: MacOS X
Classifier: Operating System :: POSIX :: Linux
Classifier: Programming Language :: Python :: 3.5
Classifier: Programming Language :: Python :: 3.6
Classifier: Programming Language :: Python :: 3.7
Classifier: Programming Language :: Python :: 3.8
Classifier: Programming Language :: Python :: 3.9
Classifier: Programming Language :: Python :: 3.10
Classifier: Programming Language :: Python :: 3.11
Classifier: Programming Language :: Python :: 3.12
Classifier: Programming Language :: Python :: 3.13
Classifier: Programming Language :: Python
Classifier: Topic :: Software Development :: Libraries
Classifier: Topic :: Utilities
License-File: LICENSE.txt
Requires-Dist: pytz
Requires-Dist: settings-helper
